LICENSE.md
README.md
dev-requirements.txt
requirements.txt
setup.py
multipy/__init__.py
multipy/version.py
multipy/runtime/CMakeLists.txt
multipy/runtime/Exception.h
multipy/runtime/README.md
multipy/runtime/benchmark.cpp
multipy/runtime/deploy.cpp
multipy/runtime/deploy.h
multipy/runtime/elf_file.cpp
multipy/runtime/elf_file.h
multipy/runtime/embedded_file.cpp
multipy/runtime/embedded_file.h
multipy/runtime/environment.h
multipy/runtime/interactive_embedded_interpreter.cpp
multipy/runtime/loader.cpp
multipy/runtime/loader.h
multipy/runtime/mem_file.h
multipy/runtime/noop_environment.h
multipy/runtime/path_environment.cpp
multipy/runtime/path_environment.h
multipy/runtime/remove_dt_needed.cpp
multipy/runtime/test_compat.py
multipy/runtime/test_deploy.cpp
multipy/runtime/test_deploy_gpu.cpp
multipy/runtime/test_deploy_lib.cpp
multipy/runtime/test_deploy_missing_interpreter.cpp
multipy/runtime/test_deploy_python.py
multipy/runtime/test_deploy_python_ext.cpp
multipy/runtime/utils.cmake
multipy/runtime/example/benchmark.cpp
multipy/runtime/example/examples.py
multipy/runtime/example/generate_examples.py
multipy/runtime/example/gpu_wrapper.py
multipy/runtime/example/simple.pt
multipy/runtime/example/tensorrt_example.py
multipy/runtime/example/fx/examples.py
multipy/runtime/example/fx/some_dependency.py
multipy/runtime/interpreter/CMakeLists.txt
multipy/runtime/interpreter/Optional.hpp
multipy/runtime/interpreter/builtin_registry.cpp
multipy/runtime/interpreter/builtin_registry.h
multipy/runtime/interpreter/hide_symbols.script
multipy/runtime/interpreter/import_find_sharedfuncptr.cpp
multipy/runtime/interpreter/import_find_sharedfuncptr.h
multipy/runtime/interpreter/interpreter_impl.cpp
multipy/runtime/interpreter/interpreter_impl.h
multipy/runtime/interpreter/plugin_registry.cpp
multipy/runtime/interpreter/plugin_registry.h
multipy/runtime/interpreter/plugin_torch.cpp
multipy/runtime/interpreter/register_frozenpython.cpp
multipy/runtime/interpreter/register_numpy.cpp
torchdeploy.egg-info/PKG-INFO
torchdeploy.egg-info/SOURCES.txt
torchdeploy.egg-info/dependency_links.txt
torchdeploy.egg-info/requires.txt
torchdeploy.egg-info/top_level.txt