Metadata-Version: 2.1
Name: torchdeploy
Version: 0.1.0.dev1
Summary: torch::deploy (multipy for non-torch uses) is a C++
Home-page: https://github.com/pytorch/multipy
Author: MultiPy Devs
Author-email: sahanp@fb.com
License: BSD-3
Keywords: pytorch,machine learning,inference
Platform: UNKNOWN
Classifier: Development Status :: 4 - Beta
Classifier: Intended Audience :: Developers
Classifier: Intended Audience :: Science/Research
Classifier: License :: OSI Approved :: BSD License
Classifier: Programming Language :: Python :: 3
Classifier: Programming Language :: Python :: 3.8
Classifier: Topic :: Scientific/Engineering :: Artificial Intelligence
Requires-Python: >=3.7
Provides-Extra: dev
License-File: LICENSE.md
